MANIFEST.in
README.md
setup.cfg
setup.py
dp_tornado/__init__.py
dp_tornado/cli.py
dp_tornado/version.py
dp_tornado.egg-info/PKG-INFO
dp_tornado.egg-info/SOURCES.txt
dp_tornado.egg-info/dependency_links.txt
dp_tornado.egg-info/entry_points.txt
dp_tornado.egg-info/requires.txt
dp_tornado.egg-info/top_level.txt
dp_tornado/engine/__init__.py
dp_tornado/engine/bootstrap.py
dp_tornado/engine/cache.py
dp_tornado/engine/config.py
dp_tornado/engine/controller.py
dp_tornado/engine/decorators.py
dp_tornado/engine/default_handler.py
dp_tornado/engine/dp_identifier_handler.py
dp_tornado/engine/engine.py
dp_tornado/engine/handler.py
dp_tornado/engine/helper.py
dp_tornado/engine/ini.py
dp_tornado/engine/loader.py
dp_tornado/engine/logger.py
dp_tornado/engine/m17n.py
dp_tornado/engine/model.py
dp_tornado/engine/namer.py
dp_tornado/engine/response.py
dp_tornado/engine/scheduler_handler.py
dp_tornado/engine/singleton.py
dp_tornado/engine/static_handler.py
dp_tornado/engine/testing.py
dp_tornado/engine/variable.py
dp_tornado/engine/view.py
dp_tornado/engine/driver/__init__.py
dp_tornado/engine/driver/memory_driver.py
dp_tornado/engine/driver/redis_driver.py
dp_tornado/engine/driver/sqlite_driver.py
dp_tornado/engine/plugin/__init__.py
dp_tornado/engine/plugin/pagination.py
dp_tornado/engine/plugin/static.py
dp_tornado/engine/plugin/ui_methods.py
dp_tornado/engine/plugin/user_agent.py
dp_tornado/engine/scheduler/__init__.py
dp_tornado/engine/scheduler/processor.py
dp_tornado/engine/schema/__init__.py
dp_tornado/engine/schema/driver/__init__.py
dp_tornado/engine/schema/driver/mysql_driver.py
dp_tornado/engine/schema/driver/sqlite_driver.py
dp_tornado/engine/static/css/dp.css
dp_tornado/engine/static/js/dp.helper.js
dp_tornado/engine/static/js/dp.js
dp_tornado/engine/static/js/dp.test.js
dp_tornado/engine/static/js/dp.ui.js
dp_tornado/engine/template/bbs/__init__.py
dp_tornado/engine/template/bbs/config.ini
dp_tornado/engine/template/bbs/config.prod.ini
dp_tornado/engine/template/bbs/config/__init__.py
dp_tornado/engine/template/bbs/config/db.py
dp_tornado/engine/template/bbs/controller/__init__.py
dp_tornado/engine/template/bbs/controller/list.py
