Metadata-Version: 1.2
Name: dp-tornado
Version: 0.9.4.21
Summary: MVC Web Application Framework with Tornado.
Home-page: http://github.com/why2pac/dp-tornado
Author: Parker
Author-email: oss@dp.farm
Maintainer: Parker
Maintainer-email: oss@dp.farm
License: MIT
Keywords: MVC,Web Application Framework
Platform: UNKNOWN
Classifier: Development Status :: 4 - Beta
Classifier: Environment :: Console
Classifier: Intended Audience :: Developers
Classifier: License :: OSI Approved :: MIT License
Classifier: Programming Language :: Python :: 2.7
Classifier: Programming Language :: Python :: 3.4
